swagger_coverage_py/__init__.py
swagger_coverage_py/configs.py
swagger_coverage_py/listener.py
swagger_coverage_py/reporter.py
swagger_coverage_py/request_schema_handler.py
swagger_coverage_py/uri.py
swagger_coverage_py/docs_writers/__init__.py
swagger_coverage_py/docs_writers/api_doc_writer.py
swagger_coverage_py/results_writers/__init__.py
swagger_coverage_py/results_writers/base_schemas_manager.py
swagger_coverage_py/results_writers/openapi_schemas_manager.py
swagger_coverage_py/results_writers/swagger_schemas_manager.py
swagger_coverage_py/swagger-coverage-commandline/bin/swagger-coverage-commandline
swagger_coverage_py/swagger-coverage-commandline/bin/swagger-coverage-commandline.bat
swagger_coverage_py/swagger-coverage-commandline/lib/btf-1.3.jar
swagger_coverage_py/swagger-coverage-commandline/lib/checker-compat-qual-2.5.5.jar
swagger_coverage_py/swagger-coverage-commandline/lib/checker-qual-3.12.0.jar
swagger_coverage_py/swagger-coverage-commandline/lib/commons-codec-1.11.jar
swagger_coverage_py/swagger-coverage-commandline/lib/commons-codec-1.9.jar
swagger_coverage_py/swagger-coverage-commandline/lib/commons-io-2.11.0.jar
swagger_coverage_py/swagger-coverage-commandline/lib/commons-io-2.6.jar
swagger_coverage_py/swagger-coverage-commandline/lib/commons-lang3-3.12.0.jar
swagger_coverage_py/swagger-coverage-commandline/lib/commons-lang3-3.7.jar
swagger_coverage_py/swagger-coverage-commandline/lib/commons-logging-1.2.jar
swagger_coverage_py/swagger-coverage-commandline/lib/error_prone_annotations-2.3.4.jar
swagger_coverage_py/swagger-coverage-commandline/lib/error_prone_annotations-2.7.1.jar
swagger_coverage_py/swagger-coverage-commandline/lib/failureaccess-1.0.1.jar
swagger_coverage_py/swagger-coverage-commandline/lib/freemarker-2.3.31.jar
swagger_coverage_py/swagger-coverage-commandline/lib/guava-28.2-android.jar
swagger_coverage_py/swagger-coverage-commandline/lib/guava-31.0.1-android.jar
swagger_coverage-3.5.1.dist-info/LICENSE
swagger_coverage-3.5.1.dist-info/METADATA
swagger_coverage-3.5.1.dist-info/WHEEL
swagger_coverage-3.5.1.dist-info/top_level.txt
swagger_coverage-3.5.1.dist-info/RECORD
