Metadata-Version: 2.1
Name: swagger-coverage
Version: 3.5.1
Summary: Python adapter for "swagger-coverage" tool
Home-page: https://github.com/JamalZeynalov/swagger-coverage-py
Author: Jamal Zeinalov
Author-email: jamal.zeynalov@gmail.com
Classifier: Programming Language :: Python :: 3
Classifier: License :: OSI Approved :: MIT License
Classifier: Operating System :: OS Independent
Requires-Python: >=3.6
License-File: LICENSE
Requires-Dist: requests >=2.31.0
Requires-Dist: Faker >=15.2.0
Requires-Dist: setuptools >=69.0.3
Requires-Dist: PyYAML >=6.0
Requires-Dist: python-dotenv >=0.21.0
Requires-Dist: rootpath ==0.1.0
Requires-Dist: environs >=9.5.0
